{
  "name": "Pembayaran",
  "plural": "Pembayaran",
  "base": "PersistedModel",
  "idInjection": true,
  "options": {
    "validateUpsert": true
  },
  "properties": {
    "Nominal": {
      "type": "number",
      "required": true
    },
    "Tanggal": {
      "type": "date",
      "required": true
    },
    "Info": {
      "type": "string"
    },
    "Ref": {
      "type": "string"
    },
    "Debit": {
      "type": "boolean",
      "required": true
    }
  },
  "validations": [],
  "relations": {},
  "acls": [],
  "methods": {}
}
